addm_toolbox/__init__.py
addm_toolbox/addm.py
addm_toolbox/addm_mla.py
addm_toolbox/addm_mla_test.py
addm_toolbox/addm_pta_map.py
addm_toolbox/addm_pta_mle.py
addm_toolbox/addm_pta_test.py
addm_toolbox/addm_toolbox_tests.py
addm_toolbox/basinhopping_optimize.py
addm_toolbox/cis_trans_fitting.py
addm_toolbox/ddm.py
addm_toolbox/ddm_mla.py
addm_toolbox/ddm_mla_test.py
addm_toolbox/ddm_pta_test.py
addm_toolbox/demo.py
addm_toolbox/genetic_algorithm_optimize.py
addm_toolbox/run_all_tests.py
addm_toolbox/simulate_addm_true_distributions.py
addm_toolbox/util.py
addm_toolbox/util_test.py
addm_toolbox/data/expdata.csv
addm_toolbox/data/fixations.csv
addm_toolbox/data/trial_conditions.csv
addm_toolbox/test_data/empty_file.csv
addm_toolbox/test_data/sample_fixations.csv
addm_toolbox/test_data/sample_fixations_incomplete.csv
addm_toolbox/test_data/sample_trial_conditions_incomplete.csv
addm_toolbox/test_data/sample_trial_data.csv
addm_toolbox/test_data/sample_trial_data_incomplete.csv
addm_toolbox/test_data/sample_trial_data_perceptual.csv
addm_toolbox/test_data/test_trial_conditions.csv
addm_toolbox-0.1.12.data/scripts/addm_basinhopping
addm_toolbox-0.1.12.data/scripts/addm_cis_trans_fit
addm_toolbox-0.1.12.data/scripts/addm_demo
addm_toolbox-0.1.12.data/scripts/addm_genetic_algorithm
addm_toolbox-0.1.12.data/scripts/addm_mla_test
addm_toolbox-0.1.12.data/scripts/addm_pta_map
addm_toolbox-0.1.12.data/scripts/addm_pta_mle
addm_toolbox-0.1.12.data/scripts/addm_pta_test
addm_toolbox-0.1.12.data/scripts/addm_simulate_true_distributions
addm_toolbox-0.1.12.data/scripts/addm_toolbox_tests
addm_toolbox-0.1.12.data/scripts/ddm_mla_test
addm_toolbox-0.1.12.data/scripts/ddm_pta_test
addm_toolbox-0.1.12.dist-info/DESCRIPTION.rst
addm_toolbox-0.1.12.dist-info/METADATA
addm_toolbox-0.1.12.dist-info/RECORD
addm_toolbox-0.1.12.dist-info/WHEEL
addm_toolbox-0.1.12.dist-info/metadata.json
addm_toolbox-0.1.12.dist-info/top_level.txt
