Metadata-Version: 2.0
Name: addm-toolbox
Version: 0.1.12
Summary: A toolbox for data analysis using the attentional drift-diffusion model.
Home-page: http://github.com/goptavares/aDDM-Toolbox
Author: Gabriela Tavares
Author-email: gtavares@caltech.edu
License: GPLv3
Download-URL: https://github.com/goptavares/aDDM-Toolbox/archive/0.1.12.tar.gz
Platform: UNKNOWN
Classifier: Programming Language :: Python :: 2.7
Classifier: Programming Language :: Python :: 3.6
Classifier: Development Status :: 3 - Alpha
Classifier: Topic :: Scientific/Engineering
Classifier: License :: OSI Approved :: GNU General Public License v3 (GPLv3)
Requires-Dist: deap
Requires-Dist: future
Requires-Dist: matplotlib
Requires-Dist: numpy
Requires-Dist: pandas
Requires-Dist: scipy
